haystack_integrations/components/generators/py.typed
haystack_integrations/components/generators/llama_stack/__init__.py
haystack_integrations/components/generators/llama_stack/chat/__init__.py
haystack_integrations/components/generators/llama_stack/chat/chat_generator.py
llama_stack_haystack-1.2.0.dist-info/METADATA
llama_stack_haystack-1.2.0.dist-info/WHEEL
llama_stack_haystack-1.2.0.dist-info/licenses/LICENSE.txt
llama_stack_haystack-1.2.0.dist-info/RECORD
