Metadata-Version: 2.4
Name: llama-stack-haystack
Version: 1.2.0
Summary: Use Llama Stack framework for text generation
Project-URL: Documentation, https://github.com/deepset-ai/haystack-core-integrations/tree/main/integrations/llama-stack#readme
Project-URL: Issues, https://github.com/deepset-ai/haystack-core-integrations/issues
Project-URL: Source, https://github.com/deepset-ai/haystack-core-integrations/tree/main/integrations/llama-stack
Author-email: deepset GmbH <info@deepset.ai>
License-Expression: Apache-2.0
License-File: LICENSE.txt
Classifier: Development Status :: 4 - Beta
Classifier: License :: OSI Approved :: Apache Software License
Classifier: Programming Language :: Python
Classifier: Programming Language :: Python :: 3.12
Classifier: Programming Language :: Python :: 3.13
Classifier: Programming Language :: Python :: Implementation :: CPython
Classifier: Programming Language :: Python :: Implementation :: PyPy
Requires-Python: >=3.12
Requires-Dist: haystack-ai>=2.19.0
Requires-Dist: llama-stack>=0.2.17
